DataFrameLabeler/DataFrameLabeler.py
DataFrameLabeler/Rowiter.py
DataFrameLabeler/__init__.py
examples/__init__.py
examples/context.py
tests/DataFrameLabeler_test.py
tests/__init__.py
tests/context.py
tests/rowiter_test.py
DataFrameLabeler-0.0.1.dist-info/LICENSE
DataFrameLabeler-0.0.1.dist-info/METADATA
DataFrameLabeler-0.0.1.dist-info/WHEEL
DataFrameLabeler-0.0.1.dist-info/top_level.txt
DataFrameLabeler-0.0.1.dist-info/RECORD
