Metadata-Version: 2.1
Name: DataFrameLabeler
Version: 0.0.1
Summary: An ipywidget helper class to manually label rows in pandas data frames.
Home-page: https://github.com/Blonck/DataFrameLabeler
Author: Martin Marenz
Author-email: martin.marenz@gmail.com
License: MIT
Platform: UNKNOWN
Classifier: Programming Language :: Python :: 3
Classifier: License :: OSI Approved :: MIT License
Classifier: Operating System :: OS Independent
